textbelt_py/__init__.py
textbelt_py/client.py
textbelt_py/decorators.py
textbelt_py/exceptions.py
textbelt_py/models.py
textbelt_py-0.1.4.dist-info/LICENSE
textbelt_py-0.1.4.dist-info/METADATA
textbelt_py-0.1.4.dist-info/WHEEL
textbelt_py-0.1.4.dist-info/RECORD
