Metadata-Version: 2.3
Name: textbelt-py
Version: 0.1.4
Summary: A Python client for Textbelt SMS API
License: MIT
Keywords: sms,textbelt,api
Author: Wahhaj Farooq
Author-email: wahhaj.farooq@pm.me
Requires-Python: >=3.10
Classifier: License :: OSI Approved :: MIT License
Classifier: Programming Language :: Python :: 3
Classifier: Programming Language :: Python :: 3.10
Classifier: Programming Language :: Python :: 3.11
Classifier: Programming Language :: Python :: 3.12
Classifier: Programming Language :: Python :: 3.13
Requires-Dist: pydantic (>=2.11.3,<3.0.0)
Requires-Dist: requests (>=2.32.3,<3.0.0)
Project-URL: Documentation, https://github.com/wfar/textbelt-py/blob/main/README.md
Project-URL: Homepage, https://github.com/wfar/textbelt-py
Project-URL: Repository, https://github.com/wfar/textbelt-py
